{
  "01K6N8STM2RGTMCGKGFW7E8D1Q.screen.home.Hello!": "Bonjour!",
  "01K6N8STMGSEN6M3W5Y00DWESC.screen.home.Livia Vaccaro": "Livia Vaccaro",
  "01K6N8STN5S9QD5Z38D4TDNMMT.screen.home.Your today’s task almost done!": "Votre tâche d'aujourd'hui est presque terminée !",
  "01K6N8STNM4DWTXHCTEWT58RXX.screen.home.View Task": "Afficher la tâche",
  "01K6N8STP557A47TQ7GM4W7MEM.screen.home.85%": "85%",
  "01K6N8STPQNENZE8YSFTX3VNVX.screen.home.In Progress": "En cours",
  "01K6N8STPWWVQESRYMH2TPYXXB.screen.home.Task Groups": "Groupes de travail",
  "01K6N8STQDW4HA1ZYF2AGMEX33.screen.home.6": "6",
  "01K6N8STQVK5J9QDXJKN7VG945.screen.home.4": "4",
  "01K6N8STRB4JJS1MJCBC4FH7JT.screen.home.Office Project": "Projet de bureau",
  "01K6N8STREFQK07DFNTG4ZYJXF.screen.home.Personal Project": "Projet personnel",
  "01K6N8STRVBSDHGC258T8B3B95.screen.home.Grocery shopping app design": "Conception d'application d'achat d'épicerie",
  "01K6N8STSF3P6J3E71V04MNDKX.screen.home.Uber Eats redesign challange": "Défi de refonte d'Uber Eats",
  "01K6N8STSVVR8F8VE3KEHWF51A.screen.home.Office Project": "Projet de bureau",
  "01K6N8STSY5MVDEJDHBTCZX8AE.screen.home.Personal Project": "Projet personnel",
  "01K6N8STTA9A6PYB8BKSYTEF76.screen.home.Daily Study": "Étude quotidienne",
  "01K6N8STTPBSN0AYQ8PCDSBHMY.screen.home.Daily Study": "Étude quotidienne",
  "01K6N8STTS14Q2P3YFB14SMHVT.screen.home.23 Tasks": "23 tâches",
  "01K6N8STV5SWAWTBHRFR4K500K.screen.home.30 Tasks": "30 tâches",
  "01K6N8STVHNQ5XAYFJ2VJMACTN.screen.home.30 Tasks": "30 tâches",
  "01K6N8STVY750G7QAS793FKTXQ.screen.home.3 Tasks": "3 tâches",
  "01K6N8STWACJST9Z1JKVS2C4D4.screen.home.70%": "70%",
  "01K6N8STWCQXTADH30T4A3J70A.screen.home.52%": "52%",
  "01K6N8STWE8J7E71QQEYPPE2SV.screen.home.87%": "87%",
  "01K6N8STWSH7D03831WWWFN57Y.screen.home.87%": "87%"
}